runtime_client.cpython-314t-aarch64-linux-gnu.so
awslambdaric/__init__.py
awslambdaric/__main__.py
awslambdaric/bootstrap.py
awslambdaric/lambda_context.py
awslambdaric/lambda_literals.py
awslambdaric/lambda_runtime_client.py
awslambdaric/lambda_runtime_exception.py
awslambdaric/lambda_runtime_hooks_runner.py
awslambdaric/lambda_runtime_log_utils.py
awslambdaric/lambda_runtime_marshaller.py
awslambdaric-3.1.1.dist-info/METADATA
awslambdaric-3.1.1.dist-info/WHEEL
awslambdaric-3.1.1.dist-info/top_level.txt
awslambdaric-3.1.1.dist-info/RECORD
awslambdaric-3.1.1.dist-info/licenses/LICENSE
awslambdaric-3.1.1.dist-info/licenses/NOTICE
