Metadata-Version: 2.1
Name: awslambdaric
Version: 3.1.1
Summary: AWS Lambda Runtime Interface Client for Python
Home-page: https://github.com/aws/aws-lambda-python-runtime-interface-client
Author: Amazon Web Services
License: UNKNOWN
Platform: UNKNOWN
Classifier: Development Status :: 5 - Production/Stable
Classifier: Intended Audience :: Developers
Classifier: Natural Language :: English
Classifier: Programming Language :: Python :: 3
Classifier: Programming Language :: Python :: 3.9
Classifier: Programming Language :: Python :: 3.10
Classifier: Programming Language :: Python :: 3.11
Classifier: Programming Language :: Python :: 3.12
Classifier: Programming Language :: Python :: 3.13
Classifier: License :: OSI Approved :: Apache Software License
Classifier: Operating System :: OS Independent
Requires-Python: >=3.9
License-File: LICENSE
License-File: NOTICE
